redis_cache_toolkit/__init__.py
redis_cache_toolkit/connection.py
redis_cache_toolkit/decorators.py
redis_cache_toolkit/geohash.py
redis_cache_toolkit/helpers.py
redis_cache_toolkit-0.1.0.dist-info/licenses/LICENSE
redis_cache_toolkit-0.1.0.dist-info/METADATA
redis_cache_toolkit-0.1.0.dist-info/WHEEL
redis_cache_toolkit-0.1.0.dist-info/top_level.txt
redis_cache_toolkit-0.1.0.dist-info/RECORD
