Metadata-Version: 2.4
Name: redis-cache-toolkit
Version: 0.1.0
Summary: Advanced Redis caching decorators with support for Pydantic models, geohash-based location caching, and multiple Redis configurations
Author-email: Umutcan Kalkan <umutcan.kalkan@gmail.com>
License: MIT
Project-URL: Homepage, https://github.com/UmutcanKalkan/redis-cache-toolkit
Project-URL: Documentation, https://github.com/UmutcanKalkan/redis-cache-toolkit#readme
Project-URL: Repository, https://github.com/UmutcanKalkan/redis-cache-toolkit
Project-URL: Issues, https://github.com/UmutcanKalkan/redis-cache-toolkit/issues
Keywords: redis,cache,caching,decorator,pydantic,geohash,location
Classifier: Development Status :: 4 - Beta
Classifier: Intended Audience :: Developers
Classifier: License :: OSI Approved :: MIT License
Classifier: Programming Language :: Python :: 3
Classifier: Programming Language :: Python :: 3.8
Classifier: Programming Language :: Python :: 3.9
Classifier: Programming Language :: Python :: 3.10
Classifier: Programming Language :: Python :: 3.11
Classifier: Programming Language :: Python :: 3.12
Classifier: Topic :: Software Development :: Libraries :: Python Modules
Classifier: Topic :: Database
Requires-Python: >=3.8
License-File: LICENSE
Requires-Dist: redis>=4.0.0
Requires-Dist: pygeohash>=1.2.0
Provides-Extra: pydantic
Requires-Dist: pydantic>=2.0.0; extra == "pydantic"
Provides-Extra: sentinel
Requires-Dist: redis[sentinel]>=4.0.0; extra == "sentinel"
Provides-Extra: cluster
Requires-Dist: redis-py-cluster>=2.1.0; extra == "cluster"
Provides-Extra: all
Requires-Dist: pydantic>=2.0.0; extra == "all"
Requires-Dist: redis[sentinel]>=4.0.0; extra == "all"
Requires-Dist: redis-py-cluster>=2.1.0; extra == "all"
Provides-Extra: dev
Requires-Dist: pytest>=7.0.0; extra == "dev"
Requires-Dist: pytest-cov>=4.0.0; extra == "dev"
Requires-Dist: pytest-asyncio>=0.21.0; extra == "dev"
Requires-Dist: black>=23.0.0; extra == "dev"
Requires-Dist: ruff>=0.1.0; extra == "dev"
Requires-Dist: mypy>=1.0.0; extra == "dev"
Requires-Dist: types-redis>=4.0.0; extra == "dev"
Dynamic: license-file
